DeBERTa/__init__.py
DeBERTa/apps/__init__.py
DeBERTa/apps/run.py
DeBERTa/apps/models/__init__.py
DeBERTa/apps/models/multi_choice.py
DeBERTa/apps/models/ner.py
DeBERTa/apps/models/sequence_classification.py
DeBERTa/apps/tasks/__init__.py
DeBERTa/apps/tasks/glue_tasks.py
DeBERTa/apps/tasks/metrics.py
DeBERTa/apps/tasks/ner_task.py
DeBERTa/apps/tasks/race_task.py
DeBERTa/apps/tasks/task.py
DeBERTa/apps/tasks/task_registry.py
DeBERTa/data/__init__.py
DeBERTa/data/dataloader.py
DeBERTa/data/dynamic_dataset.py
DeBERTa/data/example.py
DeBERTa/deberta/__init__.py
DeBERTa/deberta/bert.py
DeBERTa/deberta/cache_utils.py
DeBERTa/deberta/config.py
DeBERTa/deberta/da_utils.py
DeBERTa/deberta/deberta.py
DeBERTa/deberta/disentangled_attention.py
DeBERTa/deberta/gpt2_bpe_utils.py
DeBERTa/deberta/gpt2_tokenizer.py
DeBERTa/deberta/mlm.py
DeBERTa/deberta/nnmodule.py
DeBERTa/deberta/ops.py
DeBERTa/deberta/pooling.py
DeBERTa/deberta/pretrained_models.py
DeBERTa/deberta/spm_tokenizer.py
DeBERTa/deberta/tokenizers.py
DeBERTa/utils/__init__.py
DeBERTa/utils/argument_types.py
DeBERTa/utils/jit_tracing.py
DeBERTa/utils/logger_util.py
DeBERTa/utils/xtqdm.py
DeBERTa-0.1.12.dist-info/LICENSE
DeBERTa-0.1.12.dist-info/METADATA
DeBERTa-0.1.12.dist-info/WHEEL
DeBERTa-0.1.12.dist-info/top_level.txt
DeBERTa-0.1.12.dist-info/RECORD
