Metadata-Version: 2.1
Name: DeBERTa
Version: 0.1.12
Summary: Decoding enhanced BERT with Disentangled Attention
Home-page: https://github.com/microsoft/DeBERTa
Author: penhe
Author-email: penhe@microsoft.com
License: MIT
Keywords: NLP deep learning transformer pytorch Attention BERT RoBERTa DeBERTa
Platform: UNKNOWN
Classifier: Programming Language :: Python :: 3
Classifier: License :: OSI Approved :: MIT License
Classifier: Operating System :: OS Independent
Requires-Python: >=3.6
Requires-Dist: nltk
Requires-Dist: spacy
Requires-Dist: numpy
Requires-Dist: pytest
Requires-Dist: regex
Requires-Dist: scipy
Requires-Dist: sklearn
Requires-Dist: tqdm
Requires-Dist: ujson
Requires-Dist: seqeval
Requires-Dist: psutil
Requires-Dist: sentencepiece
Requires-Dist: laser
Requires-Dist: torch
Provides-Extra: docs
Requires-Dist: recommonmark ; extra == 'docs'
Requires-Dist: sphinx ; extra == 'docs'
Requires-Dist: sphinx-markdown-tables ; extra == 'docs'
Requires-Dist: sphinx-rtd-theme ; extra == 'docs'
